setup.py
apirator/__init__.py
apirator/models.py
apirator/tests.py
apirator/utils.py
apirator.egg-info/PKG-INFO
apirator.egg-info/SOURCES.txt
apirator.egg-info/dependency_links.txt
apirator.egg-info/requires.txt
apirator.egg-info/top_level.txt
apirator.egg-info/zip-safe