Metadata-Version: 1.0
Name: apirator
Version: 0.1.0
Summary: easily add simple http api to your django web app
Home-page: https://github.com/barbuza/apirator
Author: Victor Kotseruba
Author-email: barbuzaster@gmail.com
License: MIT
Keywords: django
Platform: UNKNOWN
